wdex/__init__.py
wdex/__main__.py
wdex/adb_handler.py
wdex/config_manager.py
wdex/csv_handler.py
wdex/feature_handler.py
wdex/game_data_getter.py
wdex/helper.py
wdex/item.py
wdex/locale_handler.py
wdex/managed_item.py
wdex/parse_save.py
wdex/patcher.py
wdex/root_handler.py
wdex/serialise_save.py
wdex/server_handler.py
wdex/tracker.py
wdex/updater.py
wdex/user_input_handler.py
wdex/edits/__init__.py
wdex/edits/basic/__init__.py
wdex/edits/basic/basic_items.py
wdex/edits/basic/catfruit.py
wdex/edits/basic/catseyes.py
wdex/edits/basic/ototo_base_mats.py
wdex/edits/basic/talent_orbs.py
wdex/edits/basic/talent_orbs_new.py
wdex/edits/cats/__init__.py
wdex/edits/cats/cat_helper.py
wdex/edits/cats/cat_id_selector.py
wdex/edits/cats/chara_drop.py
wdex/edits/cats/clear_cat_guide.py
wdex/edits/cats/evolve_cats.py
wdex/edits/cats/get_remove_cats.py
wdex/edits/cats/talents.py
wdex/edits/cats/upgrade_blue.py
wdex/edits/cats/upgrade_cats.py
wdex/edits/gamototo/__init__.py
wdex/edits/gamototo/fix_gamatoto.py
wdex/edits/gamototo/gamatoto_xp.py
wdex/edits/gamototo/helpers.py
wdex/edits/gamototo/ototo_cat_cannon.py
wdex/edits/levels/__init__.py
wdex/edits/levels/aku.py
wdex/edits/levels/allow_filibuster_clearing.py
wdex/edits/levels/behemoth_culling.py
wdex/edits/levels/clear_tutorial.py
wdex/edits/levels/enigma_stages.py
wdex/edits/levels/event_stages.py
wdex/edits/levels/gauntlet.py
wdex/edits/levels/itf_timed_scores.py
wdex/edits/levels/legend_quest.py
wdex/edits/levels/main_story.py
wdex/edits/levels/outbreaks.py
wdex/edits/levels/story_level_id_selector.py
wdex/edits/levels/towers.py
wdex/edits/levels/treasures.py
wdex/edits/levels/uncanny.py
wdex/edits/levels/unlock_aku_realm.py
wdex/edits/other/__init__.py
wdex/edits/other/cat_shrine.py
wdex/edits/other/claim_user_rank_rewards.py
wdex/edits/other/create_new_account.py
wdex/edits/other/fix_elsewhere.py
wdex/edits/other/fix_time_issues.py
wdex/edits/other/get_gold_pass.py
wdex/edits/other/meow_medals.py
wdex-1.0.1.dist-info/METADATA
wdex-1.0.1.dist-info/WHEEL
wdex-1.0.1.dist-info/top_level.txt
wdex-1.0.1.dist-info/RECORD
