Metadata-Version: 2.1
Name: wdex
Version: 1.0.1
Summary: This is a project developed by Serem for development purposes
Home-page: https://github.com/hayul0629/wdex
Author: serem
Author-email: gangh9230@gmail.com
Keywords: serem
Classifier: Programming Language :: Python :: 3.6
Classifier: Programming Language :: Python :: 3.7
Classifier: Programming Language :: Python :: 3.8
Classifier: Programming Language :: Python :: 3.9
Requires-Python: >=3.9
Requires-Dist: colored (==1.4.4)
Requires-Dist: tk
Requires-Dist: python-dateutil
Requires-Dist: requests
Requires-Dist: pyyaml
